cloudera/cdp/model/__init__.py
cloudera/cdp/model/cde.py
cloudera/cdp/security/__init__.py
cloudera/cdp/security/cde_security.py
cloudera/cdp/security/cdp_security.py
cloudera/cdp/security/token_cache.py
cloudera/cdp/security/cdp_requests/__init__.py
cloudera/cdp/security/cdp_requests/cdpcurl.py
cloudera/cdp/security/cdp_requests/cdpv1sign.py
cloudera_cde_sdk-1.0.2.dist-info/LICENSE
cloudera_cde_sdk-1.0.2.dist-info/METADATA
cloudera_cde_sdk-1.0.2.dist-info/WHEEL
cloudera_cde_sdk-1.0.2.dist-info/top_level.txt
cloudera_cde_sdk-1.0.2.dist-info/RECORD
